{"type": "SourceUnit", "children": [{"type": "PragmaDirective", "name": "solidity", "value": "0.4.25"}, {"type": "ContractDefinition", "name": "Ownable", "baseContracts": [], "subNodes": [{"type": "StateVariableDeclaration", "variables": [{"type": "VariableDeclaration", "typeName": {"type": "ElementaryTypeName", "name": "address"}, "name": "owner", "expression": null, "visibility": "public", "isStateVar": true, "isDeclaredConst": false, "isIndexed": false}], "initialValue": null}, {"type": "EventDefinition", "name": "OwnershipRenounced", "parameters": {"type": "ParameterList", "parameters": [{"type": "VariableDeclaration", "typeName": {"type": "ElementaryTypeName", "name": "address"}, "name": "previousOwner", "isStateVar": false, "isIndexed": true}]}, "isAnonymous": false}, {"type": "EventDefinition", "name": "OwnershipTransferred", "parameters": {"type": "ParameterList", "parameters": [{"type": "VariableDeclaration", "typeName": {"type": "ElementaryTypeName", "name": "address"}, "name": "previousOwner", "isStateVar": false, "isIndexed": true}, {"type": "VariableDeclaration", "typeName": {"type": "ElementaryTypeName", "name": "address"}, "name": "newOwner", "isStateVar": false, "isIndexed": true}]}, "isAnonymous": false}, {"type": "FunctionDefinition", "name": null, "parameters": {"type": "ParameterList", "parameters": []}, "returnParameters": null, "body": {"type": "Block", "statements": [{"type": "ExpressionStatement", "expression": {"type": "BinaryOperation", "operator": "=", "left": {"type": "Identifier", "name": "owner"}, "right": {"type": "MemberAccess", "expression": {"type": "Identifier", "name": "msg"}, "memberName": "sender"}}}]}, "visibility": "public", "modifiers": [], "isConstructor": true, "stateMutability": null}, {"type": "ModifierDefinition", "name": "onlyOwner", "parameters": {"type": "ParameterList", "parameters": []}, "body": {"type": "Block", "statements": [{"type": "ExpressionStatement", "expression": {"type": "FunctionCall", "expression": {"type": "Identifier", "name": "require"}, "arguments": [{"type": "BinaryOperation", "operator": "==", "left": {"type": "MemberAccess", "expression": {"type": "Identifier", "name": "msg"}, "memberName": "sender"}, "right": {"type": "Identifier", "name": "owner"}}], "names": []}}, {"type": "ExpressionStatement", "expression": {"type": "Identifier", "name": "_"}}]}}, {"type": "FunctionDefinition", "name": "renounceOwnership", "parameters": {"type": "ParameterList", "parameters": []}, "returnParameters": [], "body": {"type": "Block", "statements": [{"type": "EmitStatement", "eventCall": {"type": "FunctionCall", "expression": {"type": "Identifier", "name": "OwnershipRenounced"}, "arguments": [{"type": "Identifier", "name": "owner"}], "names": []}}, {"type": "ExpressionStatement", "expression": {"type": "BinaryOperation", "operator": "=", "left": {"type": "Identifier", "name": "owner"}, "right": {"type": "FunctionCall", "expression": {"type": "ElementaryTypeNameExpression", "typeName": {"type": "ElementaryTypeName", "name": "address"}}, "arguments": [{"type": "NumberLiteral", "number": "0", "subdenomination": null}], "names": []}}}]}, "visibility": "public", "modifiers": [{"type": "ModifierInvocation", "name": "onlyOwner", "arguments": []}], "isConstructor": false, "stateMutability": null}, {"type": "FunctionDefinition", "name": "transferOwnership", "parameters": {"type": "ParameterList", "parameters": [{"type": "Parameter", "typeName": {"type": "ElementaryTypeName", "name": "address"}, "name": "_newOwner", "storageLocation": null, "isStateVar": false, "isIndexed": false}]}, "returnParameters": [], "body": {"type": "Block", "statements": [{"type": "ExpressionStatement", "expression": {"type": "FunctionCall", "expression": {"type": "Identifier", "name": "_transferOwnership"}, "arguments": [{"type": "Identifier", "name": "_newOwner"}], "names": []}}]}, "visibility": "public", "modifiers": [{"type": "ModifierInvocation", "name": "onlyOwner", "arguments": []}], "isConstructor": false, "stateMutability": null}, {"type": "FunctionDefinition", "name": "_transferOwnership", "parameters": {"type": "ParameterList", "parameters": [{"type": "Parameter", "typeName": {"type": "ElementaryTypeName", "name": "address"}, "name": "_newOwner", "storageLocation": null, "isStateVar": false, "isIndexed": false}]}, "returnParameters": [], "body": {"type": "Block", "statements": [{"type": "ExpressionStatement", "expression": {"type": "FunctionCall", "expression": {"type": "Identifier", "name": "require"}, "arguments": [{"type": "BinaryOperation", "operator": "!=", "left": {"type": "Identifier", "name": "_newOwner"}, "right": {"type": "FunctionCall", "expression": {"type": "ElementaryTypeNameExpression", "typeName": {"type": "ElementaryTypeName", "name": "address"}}, "arguments": [{"type": "NumberLiteral", "number": "0", "subdenomination": null}], "names": []}}], "names": []}}, {"type": "EmitStatement", "eventCall": {"type": "FunctionCall", "expression": {"type": "Identifier", "name": "OwnershipTransferred"}, "arguments": [{"type": "Identifier", "name": "owner"}, {"type": "Identifier", "name": "_newOwner"}], "names": []}}, {"type": "ExpressionStatement", "expression": {"type": "BinaryOperation", "operator": "=", "left": {"type": "Identifier", "name": "owner"}, "right": {"type": "Identifier", "name": "_newOwner"}}}]}, "visibility": "internal", "modifiers": [], "isConstructor": false, "stateMutability": null}], "kind": "contract"}, {"type": "ContractDefinition", "name": "Claimable", "baseContracts": [{"type": "InheritanceSpecifier", "baseName": {"type": "UserDefinedTypeName", "namePath": "Ownable"}, "arguments": []}], "subNodes": [{"type": "StateVariableDeclaration", "variables": [{"type": "VariableDeclaration", "typeName": {"type": "ElementaryTypeName", "name": "address"}, "name": "pendingOwner", "expression": null, "visibility": "public", "isStateVar": true, "isDeclaredConst": false, "isIndexed": false}], "initialValue": null}, {"type": "ModifierDefinition", "name": "onlyPendingOwner", "parameters": {"type": "ParameterList", "parameters": []}, "body": {"type": "Block", "statements": [{"type": "ExpressionStatement", "expression": {"type": "FunctionCall", "expression": {"type": "Identifier", "name": "require"}, "arguments": [{"type": "BinaryOperation", "operator": "==", "left": {"type": "MemberAccess", "expression": {"type": "Identifier", "name": "msg"}, "memberName": "sender"}, "right": {"type": "Identifier", "name": "pendingOwner"}}], "names": []}}, {"type": "ExpressionStatement", "expression": {"type": "Identifier", "name": "_"}}]}}, {"type": "FunctionDefinition", "name": "transferOwnership", "parameters": {"type": "ParameterList", "parameters": [{"type": "Parameter", "typeName": {"type": "ElementaryTypeName", "name": "address"}, "name": "newOwner", "storageLocation": null, "isStateVar": false, "isIndexed": false}]}, "returnParameters": [], "body": {"type": "Block", "statements": [{"type": "ExpressionStatement", "expression": {"type": "BinaryOperation", "operator": "=", "left": {"type": "Identifier", "name": "pendingOwner"}, "right": {"type": "Identifier", "name": "newOwner"}}}]}, "visibility": "public", "modifiers": [{"type": "ModifierInvocation", "name": "onlyOwner", "arguments": []}], "isConstructor": false, "stateMutability": null}, {"type": "FunctionDefinition", "name": "claimOwnership", "parameters": {"type": "ParameterList", "parameters": []}, "returnParameters": [], "body": {"type": "Block", "statements": [{"type": "EmitStatement", "eventCall": {"type": "FunctionCall", "expression": {"type": "Identifier", "name": "OwnershipTransferred"}, "arguments": [{"type": "Identifier", "name": "owner"}, {"type": "Identifier", "name": "pendingOwner"}], "names": []}}, {"type": "ExpressionStatement", "expression": {"type": "BinaryOperation", "operator": "=", "left": {"type": "Identifier", "name": "owner"}, "right": {"type": "Identifier", "name": "pendingOwner"}}}, {"type": "ExpressionStatement", "expression": {"type": "BinaryOperation", "operator": "=", "left": {"type": "Identifier", "name": "pendingOwner"}, "right": {"type": "FunctionCall", "expression": {"type": "ElementaryTypeNameExpression", "typeName": {"type": "ElementaryTypeName", "name": "address"}}, "arguments": [{"type": "NumberLiteral", "number": "0", "subdenomination": null}], "names": []}}}]}, "visibility": "public", "modifiers": [{"type": "ModifierInvocation", "name": "onlyPendingOwner", "arguments": []}], "isConstructor": false, "stateMutability": null}], "kind": "contract"}, {"type": "ContractDefinition", "name": "Adminable", "baseContracts": [{"type": "InheritanceSpecifier", "baseName": {"type": "UserDefinedTypeName", "namePath": "Claimable"}, "arguments": []}], "subNodes": [{"type": "StateVariableDeclaration", "variables": [{"type": "VariableDeclaration", "typeName": {"type": "ArrayTypeName", "baseTypeName": {"type": "ElementaryTypeName", "name": "address"}, "length": null}, "name": "adminArray", "expression": null, "visibility": "public", "isStateVar": true, "isDeclaredConst": false, "isIndexed": false}], "initialValue": null}, {"type": "StructDefinition", "name": "AdminInfo", "members": [{"type": "VariableDeclaration", "typeName": {"type": "ElementaryTypeName", "name": "bool"}, "name": "valid", "storageLocation": null}, {"type": "VariableDeclaration", "typeName": {"type": "ElementaryTypeName", "name": "uint256"}, "name": "index", "storageLocation": null}]}, {"type": "StateVariableDeclaration", "variables": [{"type": "VariableDeclaration", "typeName": {"type": "Mapping", "keyType": {"type": "ElementaryTypeName", "name": "address"}, "valueType": {"type": "UserDefinedTypeName", "namePath": "AdminInfo"}}, "name": "adminTable", "expression": null, "visibility": "public", "isStateVar": true, "isDeclaredConst": false, "isIndexed": false}], "initialValue": null}, {"type": "EventDefinition", "name": "AdminAccepted", "parameters": {"type": "ParameterList", "parameters": [{"type": "VariableDeclaration", "typeName": {"type": "ElementaryTypeName", "name": "address"}, "name": "_admin", "isStateVar": false, "isIndexed": true}]}, "isAnonymous": false}, {"type": "EventDefinition", "name": "AdminRejected", "parameters": {"type": "ParameterList", "parameters": [{"type": "VariableDeclaration", "typeName": {"type": "ElementaryTypeName", "name": "address"}, "name": "_admin", "isStateVar": false, "isIndexed": true}]}, "isAnonymous": false}, {"type": "ModifierDefinition", "name": "onlyAdmin", "parameters": {"type": "ParameterList", "parameters": []}, "body": {"type": "Block", "statements": [{"type": "ExpressionStatement", "expression": {"type": "FunctionCall", "expression": {"type": "Identifier", "name": "require"}, "arguments": [{"type": "MemberAccess", "expression": {"type": "IndexAccess", "base": {"type": "Identifier", "name": "adminTable"}, "index": {"type": "MemberAccess", "expression": {"type": "Identifier", "name": "msg"}, "memberName": "sender"}}, "memberName": "valid"}, {"type": "StringLiteral", "value": "caller is illegal"}], "names": []}}, {"type": "ExpressionStatement", "expression": {"type": "Identifier", "name": "_"}}]}}, {"type": "FunctionDefinition", "name": "accept", "parameters": {"type": "ParameterList", "parameters": [{"type": "Parameter", "typeName": {"type": "ElementaryTypeName", "name": "address"}, "name": "_admin", "storageLocation": null, "isStateVar": false, "isIndexed": false}]}, "returnParameters": [], "body": {"type": "Block", "statements": [{"type": "ExpressionStatement", "expression": {"type": "FunctionCall", "expression": {"type": "Identifier", "name": "require"}, "arguments": [{"type": "BinaryOperation", "operator": "!=", "left": {"type": "Identifier", "name": "_admin"}, "right": {"type": "FunctionCall", "expression": {"type": "ElementaryTypeNameExpression", "typeName": {"type": "ElementaryTypeName", "name": "address"}}, "arguments": [{"type": "NumberLiteral", "number": "0", "subdenomination": null}], "names": []}}, {"type": "StringLiteral", "value": "administrator is illegal"}], "names": []}}, {"type": "VariableDeclarationStatement", "variables": [{"type": "VariableDeclaration", "typeName": {"type": "UserDefinedTypeName", "namePath": "AdminInfo"}, "name": "adminInfo", "storageLocation": "storage"}], "initialValue": {"type": "IndexAccess", "base": {"type": "Identifier", "name": "adminTable"}, "index": {"type": "Identifier", "name": "_admin"}}}, {"type": "ExpressionStatement", "expression": {"type": "FunctionCall", "expression": {"type": "Identifier", "name": "require"}, "arguments": [{"type": "UnaryOperation", "operator": "!", "subExpression": {"type": "MemberAccess", "expression": {"type": "Identifier", "name": "adminInfo"}, "memberName": "valid"}, "isPrefix": true}, {"type": "StringLiteral", "value": "administrator is already accepted"}], "names": []}}, {"type": "ExpressionStatement", "expression": {"type": "BinaryOperation", "operator": "=", "left": {"type": "MemberAccess", "expression": {"type": "Identifier", "name": "adminInfo"}, "memberName": "valid"}, "right": {"type": "BooleanLiteral", "value": true}}}, {"type": "ExpressionStatement", "expression": {"type": "BinaryOperation", "operator": "=", "left": {"type": "MemberAccess", "expression": {"type": "Identifier", "name": "adminInfo"}, "memberName": "index"}, "right": {"type": "MemberAccess", "expression": {"type": "Identifier", "name": "adminArray"}, "memberName": "length"}}}, {"type": "ExpressionStatement", "expression": {"type": "FunctionCall", "expression": {"type": "MemberAccess", "expression": {"type": "Identifier", "name": "adminArray"}, "memberName": "push"}, "arguments": [{"type": "Identifier", "name": "_admin"}], "names": []}}, {"type": "EmitStatement", "eventCall": {"type": "FunctionCall", "expression": {"type": "Identifier", "name": "AdminAccepted"}, "arguments": [{"type": "Identifier", "name": "_admin"}], "names": []}}]}, "visibility": "external", "modifiers": [{"type": "ModifierInvocation", "name": "onlyOwner", "arguments": []}], "isConstructor": false, "stateMutability": null}, {"type": "FunctionDefinition", "name": "reject", "parameters": {"type": "ParameterList", "parameters": [{"type": "Parameter", "typeName": {"type": "ElementaryTypeName", "name": "address"}, "name": "_admin", "storageLocation": null, "isStateVar": false, "isIndexed": false}]}, "returnParameters": [], "body": {"type": "Block", "statements": [{"type": "VariableDeclarationStatement", "variables": [{"type": "VariableDeclaration", "typeName": {"type": "UserDefinedTypeName", "namePath": "AdminInfo"}, "name": "adminInfo", "storageLocation": "storage"}], "initialValue": {"type": "IndexAccess", "base": {"type": "Identifier", "name": "adminTable"}, "index": {"type": "Identifier", "name": "_admin"}}}, {"type": "ExpressionStatement", "expression": {"type": "FunctionCall", "expression": {"type": "Identifier", "name": "require"}, "arguments": [{"type": "BinaryOperation", "operator": ">", "left": {"type": "MemberAccess", "expression": {"type": "Identifier", "name": "adminArray"}, "memberName": "length"}, "right": {"type": "MemberAccess", "expression": {"type": "Identifier", "name": "adminInfo"}, "memberName": "index"}}, {"type": "StringLiteral", "value": "administrator is already rejected"}], "names": []}}, {"type": "ExpressionStatement", "expression": {"type": "FunctionCall", "expression": {"type": "Identifier", "name": "require"}, "arguments": [{"type": "BinaryOperation", "operator": "==", "left": {"type": "Identifier", "name": "_admin"}, "right": {"type": "IndexAccess", "base": {"type": "Identifier", "name": "adminArray"}, "index": {"type": "MemberAccess", "expression": {"type": "Identifier", "name": "adminInfo"}, "memberName": "index"}}}, {"type": "StringLiteral", "value": "administrator is already rejected"}], "names": []}}, {"type": "VariableDeclarationStatement", "variables": [{"type": "VariableDeclaration", "typeName": {"type": "ElementaryTypeName", "name": "address"}, "name": "lastAdmin", "storageLocation": null}], "initialValue": {"type": "IndexAccess", "base": {"type": "Identifier", "name": "adminArray"}, "index": {"type": "BinaryOperation", "operator": "-", "left": {"type": "MemberAccess", "expression": {"type": "Identifier", "name": "adminArray"}, "memberName": "length"}, "right": {"type": "NumberLiteral", "number": "1", "subdenomination": null}}}}, {"type": "ExpressionStatement", "expression": {"type": "BinaryOperation", "operator": "=", "left": {"type": "MemberAccess", "expression": {"type": "IndexAccess", "base": {"type": "Identifier", "name": "adminTable"}, "index": {"type": "Identifier", "name": "lastAdmin"}}, "memberName": "index"}, "right": {"type": "MemberAccess", "expression": {"type": "Identifier", "name": "adminInfo"}, "memberName": "index"}}}, {"type": "ExpressionStatement", "expression": {"type": "BinaryOperation", "operator": "=", "left": {"type": "IndexAccess", "base": {"type": "Identifier", "name": "adminArray"}, "index": {"type": "MemberAccess", "expression": {"type": "Identifier", "name": "adminInfo"}, "memberName": "index"}}, "right": {"type": "Identifier", "name": "lastAdmin"}}}, {"type": "ExpressionStatement", "expression": {"type": "BinaryOperation", "operator": "-=", "left": {"type": "MemberAccess", "expression": {"type": "Identifier", "name": "adminArray"}, "memberName": "length"}, "right": {"type": "NumberLiteral", "number": "1", "subdenomination": null}}}, {"type": "ExpressionStatement", "expression": {"type": "UnaryOperation", "operator": "delete", "subExpression": {"type": "IndexAccess", "base": {"type": "Identifier", "name": "adminTable"}, "index": {"type": "Identifier", "name": "_admin"}}, "isPrefix": true}}, {"type": "EmitStatement", "eventCall": {"type": "FunctionCall", "expression": {"type": "Identifier", "name": "AdminRejected"}, "arguments": [{"type": "Identifier", "name": "_admin"}], "names": []}}]}, "visibility": "external", "modifiers": [{"type": "ModifierInvocation", "name": "onlyOwner", "arguments": []}], "isConstructor": false, "stateMutability": null}, {"type": "FunctionDefinition", "name": "getAdminArray", "parameters": {"type": "ParameterList", "parameters": []}, "returnParameters": {"type": "ParameterList", "parameters": [{"type": "Parameter", "typeName": {"type": "ArrayTypeName", "baseTypeName": {"type": "ElementaryTypeName", "name": "address"}, "length": null}, "name": null, "storageLocation": "memory", "isStateVar": false, "isIndexed": false}]}, "body": {"type": "Block", "statements": [{"type": "Identifier", "name": "adminArray"}]}, "visibility": "external", "modifiers": [], "isConstructor": false, "stateMutability": "view"}, {"type": "FunctionDefinition", "name": "getAdminCount", "parameters": {"type": "ParameterList", "parameters": []}, "returnParameters": {"type": "ParameterList", "parameters": [{"type": "Parameter", "typeName": {"type": "ElementaryTypeName", "name": "uint256"}, "name": null, "storageLocation": null, "isStateVar": false, "isIndexed": false}]}, "body": {"type": "Block", "statements": [{"type": "MemberAccess", "expression": {"type": "Identifier", "name": "adminArray"}, "memberName": "length"}]}, "visibility": "external", "modifiers": [], "isConstructor": false, "stateMutability": "view"}], "kind": "contract"}, {"type": "ContractDefinition", "name": "IAuthorizationDataSource", "baseContracts": [], "subNodes": [{"type": "FunctionDefinition", "name": "getAuthorizedActionRole", "parameters": {"type": "ParameterList", "parameters": [{"type": "Parameter", "typeName": {"type": "ElementaryTypeName", "name": "address"}, "name": "_wallet", "storageLocation": null, "isStateVar": false, "isIndexed": false}]}, "returnParameters": {"type": "ParameterList", "parameters": [{"type": "Parameter", "typeName": {"type": "ElementaryTypeName", "name": "bool"}, "name": null, "storageLocation": null, "isStateVar": false, "isIndexed": false}, {"type": "Parameter", "typeName": {"type": "ElementaryTypeName", "name": "uint256"}, "name": null, "storageLocation": null, "isStateVar": false, "isIndexed": false}]}, "body": [], "visibility": "external", "modifiers": [], "isConstructor": false, "stateMutability": "view"}, {"type": "FunctionDefinition", "name": "getAuthorizedActionRoleAndClass", "parameters": {"type": "ParameterList", "parameters": [{"type": "Parameter", "typeName": {"type": "ElementaryTypeName", "name": "address"}, "name": "_wallet", "storageLocation": null, "isStateVar": false, "isIndexed": false}]}, "returnParameters": {"type": "ParameterList", "parameters": [{"type": "Parameter", "typeName": {"type": "ElementaryTypeName", "name": "bool"}, "name": null, "storageLocation": null, "isStateVar": false, "isIndexed": false}, {"type": "Parameter", "typeName": {"type": "ElementaryTypeName", "name": "uint256"}, "name": null, "storageLocation": null, "isStateVar": false, "isIndexed": false}, {"type": "Parameter", "typeName": {"type": "ElementaryTypeName", "name": "uint256"}, "name": null, "storageLocation": null, "isStateVar": false, "isIndexed": false}]}, "body": [], "visibility": "external", "modifiers": [], "isConstructor": false, "stateMutability": "view"}, {"type": "FunctionDefinition", "name": "getTradeLimitsAndClass", "parameters": {"type": "ParameterList", "parameters": [{"type": "Parameter", "typeName": {"type": "ElementaryTypeName", "name": "address"}, "name": "_wallet", "storageLocation": null, "isStateVar": false, "isIndexed": false}]}, "returnParameters": {"type": "ParameterList", "parameters": [{"type": "Parameter", "typeName": {"type": "ElementaryTypeName", "name": "uint256"}, "name": null, "storageLocation": null, "isStateVar": false, "isIndexed": false}, {"type": "Parameter", "typeName": {"type": "ElementaryTypeName", "name": "uint256"}, "name": null, "storageLocation": null, "isStateVar": false, "isIndexed": false}, {"type": "Parameter", "typeName": {"type": "ElementaryTypeName", "name": "uint256"}, "name": null, "storageLocation": null, "isStateVar": false, "isIndexed": false}]}, "body": [], "visibility": "external", "modifiers": [], "isConstructor": false, "stateMutability": "view"}, {"type": "FunctionDefinition", "name": "getBuyTradeLimitAndClass", "parameters": {"type": "ParameterList", "parameters": [{"type": "Parameter", "typeName": {"type": "ElementaryTypeName", "name": "address"}, "name": "_wallet", "storageLocation": null, "isStateVar": false, "isIndexed": false}]}, "returnParameters": {"type": "ParameterList", "parameters": [{"type": "Parameter", "typeName": {"type": "ElementaryTypeName", "name": "uint256"}, "name": null, "storageLocation": null, "isStateVar": false, "isIndexed": false}, {"type": "Parameter", "typeName": {"type": "ElementaryTypeName", "name": "uint256"}, "name": null, "storageLocation": null, "isStateVar": false, "isIndexed": false}]}, "body": [], "visibility": "external", "modifiers": [], "isConstructor": false, "stateMutability": "view"}, {"type": "FunctionDefinition", "name": "getSellTradeLimitAndClass", "parameters": {"type": "ParameterList", "parameters": [{"type": "Parameter", "typeName": {"type": "ElementaryTypeName", "name": "address"}, "name": "_wallet", "storageLocation": null, "isStateVar": false, "isIndexed": false}]}, "returnParameters": {"type": "ParameterList", "parameters": [{"type": "Parameter", "typeName": {"type": "ElementaryTypeName", "name": "uint256"}, "name": null, "storageLocation": null, "isStateVar": false, "isIndexed": false}, {"type": "Parameter", "typeName": {"type": "ElementaryTypeName", "name": "uint256"}, "name": null, "storageLocation": null, "isStateVar": false, "isIndexed": false}]}, "body": [], "visibility": "external", "modifiers": [], "isConstructor": false, "stateMutability": "view"}], "kind": "interface"}, {"type": "ContractDefinition", "name": "AuthorizationDataSource", "baseContracts": [{"type": "InheritanceSpecifier", "baseName": {"type": "UserDefinedTypeName", "namePath": "IAuthorizationDataSource"}, "arguments": []}, {"type": "InheritanceSpecifier", "baseName": {"type": "UserDefinedTypeName", "namePath": "Adminable"}, "arguments": []}], "subNodes": [{"type": "StateVariableDeclaration", "variables": [{"type": "VariableDeclaration", "typeName": {"type": "ElementaryTypeName", "name": "string"}, "name": "VERSION", "expression": {"type": "StringLiteral", "value": "2.0.0"}, "visibility": "public", "isStateVar": true, "isDeclaredConst": true, "isIndexed": false}], "initialValue": {"type": "StringLiteral", "value": "2.0.0"}}, {"type": "StateVariableDeclaration", "variables": [{"type": "VariableDeclaration", "typeName": {"type": "ElementaryTypeName", "name": "uint256"}, "name": "walletCount", "expression": null, "visibility": "public", "isStateVar": true, "isDeclaredConst": false, "isIndexed": false}], "initialValue": null}, {"type": "StructDefinition", "name": "WalletInfo", "members": [{"type": "VariableDeclaration", "typeName": {"type": "ElementaryTypeName", "name": "uint256"}, "name": "sequenceNum", "storageLocation": null}, {"type": "VariableDeclaration", "typeName": {"type": "ElementaryTypeName", "name": "bool"}, "name": "isWhitelisted", "storageLocation": null}, {"type": "VariableDeclaration", "typeName": {"type": "ElementaryTypeName", "name": "uint256"}, "name": "actionRole", "storageLocation": null}, {"type": "VariableDeclaration", "typeName": {"type": "ElementaryTypeName", "name": "uint256"}, "name": "buyLimit", "storageLocation": null}, {"type": "VariableDeclaration", "typeName": {"type": "ElementaryTypeName", "name": "uint256"}, "name": "sellLimit", "storageLocation": null}, {"type": "VariableDeclaration", "typeName": {"type": "ElementaryTypeName", "name": "uint256"}, "name": "tradeClass", "storageLocation": null}]}, {"type": "StateVariableDeclaration", "variables": [{"type": "VariableDeclaration", "typeName": {"type": "Mapping", "keyType": {"type": "ElementaryTypeName", "name": "address"}, "valueType": {"type": "UserDefinedTypeName", "namePath": "WalletInfo"}}, "name": "walletTable", "expression": null, "visibility": "public", "isStateVar": true, "isDeclaredConst": false, "isIndexed": false}], "initialValue": null}, {"type": "EventDefinition", "name": "WalletSaved", "parameters": {"type": "ParameterList", "parameters": [{"type": "VariableDeclaration", "typeName": {"type": "ElementaryTypeName", "name": "address"}, "name": "_wallet", "isStateVar": false, "isIndexed": true}]}, "isAnonymous": false}, {"type": "EventDefinition", "name": "WalletDeleted", "parameters": {"type": "ParameterList", "parameters": [{"type": "VariableDeclaration", "typeName": {"type": "ElementaryTypeName", "name": "address"}, "name": "_wallet", "isStateVar": false, "isIndexed": true}]}, "isAnonymous": false}, {"type": "EventDefinition", "name": "WalletNotSaved", "parameters": {"type": "ParameterList", "parameters": [{"type": "VariableDeclaration", "typeName": {"type": "ElementaryTypeName", "name": "address"}, "name": "_wallet", "isStateVar": false, "isIndexed": true}]}, "isAnonymous": false}, {"type": "EventDefinition", "name": "WalletNotDeleted", "parameters": {"type": "ParameterList", "parameters": [{"type": "VariableDeclaration", "typeName": {"type": "ElementaryTypeName", "name": "address"}, "name": "_wallet", "isStateVar": false, "isIndexed": true}]}, "isAnonymous": false}, {"type": "FunctionDefinition", "name": "getAuthorizedActionRole", "parameters": {"type": "ParameterList", "parameters": [{"type": "Parameter", "typeName": {"type": "ElementaryTypeName", "name": "address"}, "name": "_wallet", "storageLocation": null, "isStateVar": false, "isIndexed": false}]}, "returnParameters": {"type": "ParameterList", "parameters": [{"type": "Parameter", "typeName": {"type": "ElementaryTypeName", "name": "bool"}, "name": null, "storageLocation": null, "isStateVar": false, "isIndexed": false}, {"type": "Parameter", "typeName": {"type": "ElementaryTypeName", "name": "uint256"}, "name": null, "storageLocation": null, "isStateVar": false, "isIndexed": false}]}, "body": {"type": "Block", "statements": [{"type": "VariableDeclarationStatement", "variables": [{"type": "VariableDeclaration", "typeName": {"type": "UserDefinedTypeName", "namePath": "WalletInfo"}, "name": "walletInfo", "storageLocation": "storage"}], "initialValue": {"type": "IndexAccess", "base": {"type": "Identifier", "name": "walletTable"}, "index": {"type": "Identifier", "name": "_wallet"}}}, {"type": "TupleExpression", "components": [{"type": "MemberAccess", "expression": {"type": "Identifier", "name": "walletInfo"}, "memberName": "isWhitelisted"}, {"type": "MemberAccess", "expression": {"type": "Identifier", "name": "walletInfo"}, "memberName": "actionRole"}], "isArray": false}]}, "visibility": "external", "modifiers": [], "isConstructor": false, "stateMutability": "view"}, {"type": "FunctionDefinition", "name": "getAuthorizedActionRoleAndClass", "parameters": {"type": "ParameterList", "parameters": [{"type": "Parameter", "typeName": {"type": "ElementaryTypeName", "name": "address"}, "name": "_wallet", "storageLocation": null, "isStateVar": false, "isIndexed": false}]}, "returnParameters": {"type": "ParameterList", "parameters": [{"type": "Parameter", "typeName": {"type": "ElementaryTypeName", "name": "bool"}, "name": null, "storageLocation": null, "isStateVar": false, "isIndexed": false}, {"type": "Parameter", "typeName": {"type": "ElementaryTypeName", "name": "uint256"}, "name": null, "storageLocation": null, "isStateVar": false, "isIndexed": false}, {"type": "Parameter", "typeName": {"type": "ElementaryTypeName", "name": "uint256"}, "name": null, "storageLocation": null, "isStateVar": false, "isIndexed": false}]}, "body": {"type": "Block", "statements": [{"type": "VariableDeclarationStatement", "variables": [{"type": "VariableDeclaration", "typeName": {"type": "UserDefinedTypeName", "namePath": "WalletInfo"}, "name": "walletInfo", "storageLocation": "storage"}], "initialValue": {"type": "IndexAccess", "base": {"type": "Identifier", "name": "walletTable"}, "index": {"type": "Identifier", "name": "_wallet"}}}, {"type": "TupleExpression", "components": [{"type": "MemberAccess", "expression": {"type": "Identifier", "name": "walletInfo"}, "memberName": "isWhitelisted"}, {"type": "MemberAccess", "expression": {"type": "Identifier", "name": "walletInfo"}, "memberName": "actionRole"}, {"type": "MemberAccess", "expression": {"type": "Identifier", "name": "walletInfo"}, "memberName": "tradeClass"}], "isArray": false}]}, "visibility": "external", "modifiers": [], "isConstructor": false, "stateMutability": "view"}, {"type": "FunctionDefinition", "name": "getTradeLimitsAndClass", "parameters": {"type": "ParameterList", "parameters": [{"type": "Parameter", "typeName": {"type": "ElementaryTypeName", "name": "address"}, "name": "_wallet", "storageLocation": null, "isStateVar": false, "isIndexed": false}]}, "returnParameters": {"type": "ParameterList", "parameters": [{"type": "Parameter", "typeName": {"type": "ElementaryTypeName", "name": "uint256"}, "name": null, "storageLocation": null, "isStateVar": false, "isIndexed": false}, {"type": "Parameter", "typeName": {"type": "ElementaryTypeName", "name": "uint256"}, "name": null, "storageLocation": null, "isStateVar": false, "isIndexed": false}, {"type": "Parameter", "typeName": {"type": "ElementaryTypeName", "name": "uint256"}, "name": null, "storageLocation": null, "isStateVar": false, "isIndexed": false}]}, "body": {"type": "Block", "statements": [{"type": "VariableDeclarationStatement", "variables": [{"type": "VariableDeclaration", "typeName": {"type": "UserDefinedTypeName", "namePath": "WalletInfo"}, "name": "walletInfo", "storageLocation": "storage"}], "initialValue": {"type": "IndexAccess", "base": {"type": "Identifier", "name": "walletTable"}, "index": {"type": "Identifier", "name": "_wallet"}}}, {"type": "TupleExpression", "components": [{"type": "MemberAccess", "expression": {"type": "Identifier", "name": "walletInfo"}, "memberName": "buyLimit"}, {"type": "MemberAccess", "expression": {"type": "Identifier", "name": "walletInfo"}, "memberName": "sellLimit"}, {"type": "MemberAccess", "expression": {"type": "Identifier", "name": "walletInfo"}, "memberName": "tradeClass"}], "isArray": false}]}, "visibility": "external", "modifiers": [], "isConstructor": false, "stateMutability": "view"}, {"type": "FunctionDefinition", "name": "getBuyTradeLimitAndClass", "parameters": {"type": "ParameterList", "parameters": [{"type": "Parameter", "typeName": {"type": "ElementaryTypeName", "name": "address"}, "name": "_wallet", "storageLocation": null, "isStateVar": false, "isIndexed": false}]}, "returnParameters": {"type": "ParameterList", "parameters": [{"type": "Parameter", "typeName": {"type": "ElementaryTypeName", "name": "uint256"}, "name": null, "storageLocation": null, "isStateVar": false, "isIndexed": false}, {"type": "Parameter", "typeName": {"type": "ElementaryTypeName", "name": "uint256"}, "name": null, "storageLocation": null, "isStateVar": false, "isIndexed": false}]}, "body": {"type": "Block", "statements": [{"type": "VariableDeclarationStatement", "variables": [{"type": "VariableDeclaration", "typeName": {"type": "UserDefinedTypeName", "namePath": "WalletInfo"}, "name": "walletInfo", "storageLocation": "storage"}], "initialValue": {"type": "IndexAccess", "base": {"type": "Identifier", "name": "walletTable"}, "index": {"type": "Identifier", "name": "_wallet"}}}, {"type": "TupleExpression", "components": [{"type": "MemberAccess", "expression": {"type": "Identifier", "name": "walletInfo"}, "memberName": "buyLimit"}, {"type": "MemberAccess", "expression": {"type": "Identifier", "name": "walletInfo"}, "memberName": "tradeClass"}], "isArray": false}]}, "visibility": "external", "modifiers": [], "isConstructor": false, "stateMutability": "view"}, {"type": "FunctionDefinition", "name": "getSellTradeLimitAndClass", "parameters": {"type": "ParameterList", "parameters": [{"type": "Parameter", "typeName": {"type": "ElementaryTypeName", "name": "address"}, "name": "_wallet", "storageLocation": null, "isStateVar": false, "isIndexed": false}]}, "returnParameters": {"type": "ParameterList", "parameters": [{"type": "Parameter", "typeName": {"type": "ElementaryTypeName", "name": "uint256"}, "name": null, "storageLocation": null, "isStateVar": false, "isIndexed": false}, {"type": "Parameter", "typeName": {"type": "ElementaryTypeName", "name": "uint256"}, "name": null, "storageLocation": null, "isStateVar": false, "isIndexed": false}]}, "body": {"type": "Block", "statements": [{"type": "VariableDeclarationStatement", "variables": [{"type": "VariableDeclaration", "typeName": {"type": "UserDefinedTypeName", "namePath": "WalletInfo"}, "name": "walletInfo", "storageLocation": "storage"}], "initialValue": {"type": "IndexAccess", "base": {"type": "Identifier", "name": "walletTable"}, "index": {"type": "Identifier", "name": "_wallet"}}}, {"type": "TupleExpression", "components": [{"type": "MemberAccess", "expression": {"type": "Identifier", "name": "walletInfo"}, "memberName": "sellLimit"}, {"type": "MemberAccess", "expression": {"type": "Identifier", "name": "walletInfo"}, "memberName": "tradeClass"}], "isArray": false}]}, "visibility": "external", "modifiers": [], "isConstructor": false, "stateMutability": "view"}, {"type": "FunctionDefinition", "name": "upsertOne", "parameters": {"type": "ParameterList", "parameters": [{"type": "Parameter", "typeName": {"type": "ElementaryTypeName", "name": "address"}, "name": "_wallet", "storageLocation": null, "isStateVar": false, "isIndexed": false}, {"type": "Parameter", "typeName": {"type": "ElementaryTypeName", "name": "uint256"}, "name": "_sequenceNum", "storageLocation": null, "isStateVar": false, "isIndexed": false}, {"type": "Parameter", "typeName": {"type": "ElementaryTypeName", "name": "bool"}, "name": "_isWhitelisted", "storageLocation": null, "isStateVar": false, "isIndexed": false}, {"type": "Parameter", "typeName": {"type": "ElementaryTypeName", "name": "uint256"}, "name": "_actionRole", "storageLocation": null, "isStateVar": false, "isIndexed": false}, {"type": "Parameter", "typeName": {"type": "ElementaryTypeName", "name": "uint256"}, "name": "_buyLimit", "storageLocation": null, "isStateVar": false, "isIndexed": false}, {"type": "Parameter", "typeName": {"type": "ElementaryTypeName", "name": "uint256"}, "name": "_sellLimit", "storageLocation": null, "isStateVar": false, "isIndexed": false}, {"type": "Parameter", "typeName": {"type": "ElementaryTypeName", "name": "uint256"}, "name": "_tradeClass", "storageLocation": null, "isStateVar": false, "isIndexed": false}]}, "returnParameters": [], "body": {"type": "Block", "statements": [{"type": "ExpressionStatement", "expression": {"type": "FunctionCall", "expression": {"type": "Identifier", "name": "_upsert"}, "arguments": [{"type": "Identifier", "name": "_wallet"}, {"type": "Identifier", "name": "_sequenceNum"}, {"type": "Identifier", "name": "_isWhitelisted"}, {"type": "Identifier", "name": "_actionRole"}, {"type": "Identifier", "name": "_buyLimit"}, {"type": "Identifier", "name": "_sellLimit"}, {"type": "Identifier", "name": "_tradeClass"}], "names": []}}]}, "visibility": "external", "modifiers": [{"type": "ModifierInvocation", "name": "onlyAdmin", "arguments": []}], "isConstructor": false, "stateMutability": null}, {"type": "FunctionDefinition", "name": "removeOne", "parameters": {"type": "ParameterList", "parameters": [{"type": "Parameter", "typeName": {"type": "ElementaryTypeName", "name": "address"}, "name": "_wallet", "storageLocation": null, "isStateVar": false, "isIndexed": false}]}, "returnParameters": [], "body": {"type": "Block", "statements": [{"type": "ExpressionStatement", "expression": {"type": "FunctionCall", "expression": {"type": "Identifier", "name": "_remove"}, "arguments": [{"type": "Identifier", "name": "_wallet"}], "names": []}}]}, "visibility": "external", "modifiers": [{"type": "ModifierInvocation", "name": "onlyAdmin", "arguments": []}], "isConstructor": false, "stateMutability": null}, {"type": "FunctionDefinition", "name": "upsertAll", "parameters": {"type": "ParameterList", "parameters": [{"type": "Parameter", "typeName": {"type": "ArrayTypeName", "baseTypeName": {"type": "ElementaryTypeName", "name": "address"}, "length": null}, "name": "_wallets", "storageLocation": null, "isStateVar": false, "isIndexed": false}, {"type": "Parameter", "typeName": {"type": "ElementaryTypeName", "name": "uint256"}, "name": "_sequenceNum", "storageLocation": null, "isStateVar": false, "isIndexed": false}, {"type": "Parameter", "typeName": {"type": "ElementaryTypeName", "name": "bool"}, "name": "_isWhitelisted", "storageLocation": null, "isStateVar": false, "isIndexed": false}, {"type": "Parameter", "typeName": {"type": "ElementaryTypeName", "name": "uint256"}, "name": "_actionRole", "storageLocation": null, "isStateVar": false, "isIndexed": false}, {"type": "Parameter", "typeName": {"type": "ElementaryTypeName", "name": "uint256"}, "name": "_buyLimit", "storageLocation": null, "isStateVar": false, "isIndexed": false}, {"type": "Parameter", "typeName": {"type": "ElementaryTypeName", "name": "uint256"}, "name": "_sellLimit", "storageLocation": null, "isStateVar": false, "isIndexed": false}, {"type": "Parameter", "typeName": {"type": "ElementaryTypeName", "name": "uint256"}, "name": "_tradeClass", "storageLocation": null, "isStateVar": false, "isIndexed": false}]}, "returnParameters": [], "body": {"type": "Block", "statements": [{"type": "ForStatement", "initExpression": {"type": "VariableDeclarationStatement", "variables": [{"type": "VariableDeclaration", "typeName": {"type": "ElementaryTypeName", "name": "uint256"}, "name": "i", "storageLocation": null}], "initialValue": {"type": "NumberLiteral", "number": "0", "subdenomination": null}}, "conditionExpression": {"type": "BinaryOperation", "operator": "<", "left": {"type": "Identifier", "name": "i"}, "right": {"type": "MemberAccess", "expression": {"type": "Identifier", "name": "_wallets"}, "memberName": "length"}}, "loopExpression": {"type": "ExpressionStatement", "expression": {"type": "UnaryOperation", "operator": "++", "subExpression": {"type": "Identifier", "name": "i"}, "isPrefix": false}}, "body": {"type": "ExpressionStatement", "expression": {"type": "FunctionCall", "expression": {"type": "Identifier", "name": "_upsert"}, "arguments": [{"type": "IndexAccess", "base": {"type": "Identifier", "name": "_wallets"}, "index": {"type": "Identifier", "name": "i"}}, {"type": "Identifier", "name": "_sequenceNum"}, {"type": "Identifier", "name": "_isWhitelisted"}, {"type": "Identifier", "name": "_actionRole"}, {"type": "Identifier", "name": "_buyLimit"}, {"type": "Identifier", "name": "_sellLimit"}, {"type": "Identifier", "name": "_tradeClass"}], "names": []}}}]}, "visibility": "external", "modifiers": [{"type": "ModifierInvocation", "name": "onlyAdmin", "arguments": []}], "isConstructor": false, "stateMutability": null}, {"type": "FunctionDefinition", "name": "removeAll", "parameters": {"type": "ParameterList", "parameters": [{"type": "Parameter", "typeName": {"type": "ArrayTypeName", "baseTypeName": {"type": "ElementaryTypeName", "name": "address"}, "length": null}, "name": "_wallets", "storageLocation": null, "isStateVar": false, "isIndexed": false}]}, "returnParameters": [], "body": {"type": "Block", "statements": [{"type": "ForStatement", "initExpression": {"type": "VariableDeclarationStatement", "variables": [{"type": "VariableDeclaration", "typeName": {"type": "ElementaryTypeName", "name": "uint256"}, "name": "i", "storageLocation": null}], "initialValue": {"type": "NumberLiteral", "number": "0", "subdenomination": null}}, "conditionExpression": {"type": "BinaryOperation", "operator": "<", "left": {"type": "Identifier", "name": "i"}, "right": {"type": "MemberAccess", "expression": {"type": "Identifier", "name": "_wallets"}, "memberName": "length"}}, "loopExpression": {"type": "ExpressionStatement", "expression": {"type": "UnaryOperation", "operator": "++", "subExpression": {"type": "Identifier", "name": "i"}, "isPrefix": false}}, "body": {"type": "ExpressionStatement", "expression": {"type": "FunctionCall", "expression": {"type": "Identifier", "name": "_remove"}, "arguments": [{"type": "IndexAccess", "base": {"type": "Identifier", "name": "_wallets"}, "index": {"type": "Identifier", "name": "i"}}], "names": []}}}]}, "visibility": "external", "modifiers": [{"type": "ModifierInvocation", "name": "onlyAdmin", "arguments": []}], "isConstructor": false, "stateMutability": null}, {"type": "FunctionDefinition", "name": "_upsert", "parameters": {"type": "ParameterList", "parameters": [{"type": "Parameter", "typeName": {"type": "ElementaryTypeName", "name": "address"}, "name": "_wallet", "storageLocation": null, "isStateVar": false, "isIndexed": false}, {"type": "Parameter", "typeName": {"type": "ElementaryTypeName", "name": "uint256"}, "name": "_sequenceNum", "storageLocation": null, "isStateVar": false, "isIndexed": false}, {"type": "Parameter", "typeName": {"type": "ElementaryTypeName", "name": "bool"}, "name": "_isWhitelisted", "storageLocation": null, "isStateVar": false, "isIndexed": false}, {"type": "Parameter", "typeName": {"type": "ElementaryTypeName", "name": "uint256"}, "name": "_actionRole", "storageLocation": null, "isStateVar": false, "isIndexed": false}, {"type": "Parameter", "typeName": {"type": "ElementaryTypeName", "name": "uint256"}, "name": "_buyLimit", "storageLocation": null, "isStateVar": false, "isIndexed": false}, {"type": "Parameter", "typeName": {"type": "ElementaryTypeName", "name": "uint256"}, "name": "_sellLimit", "storageLocation": null, "isStateVar": false, "isIndexed": false}, {"type": "Parameter", "typeName": {"type": "ElementaryTypeName", "name": "uint256"}, "name": "_tradeClass", "storageLocation": null, "isStateVar": false, "isIndexed": false}]}, "returnParameters": [], "body": {"type": "Block", "statements": [{"type": "ExpressionStatement", "expression": {"type": "FunctionCall", "expression": {"type": "Identifier", "name": "require"}, "arguments": [{"type": "BinaryOperation", "operator": "!=", "left": {"type": "Identifier", "name": "_wallet"}, "right": {"type": "FunctionCall", "expression": {"type": "ElementaryTypeNameExpression", "typeName": {"type": "ElementaryTypeName", "name": "address"}}, "arguments": [{"type": "NumberLiteral", "number": "0", "subdenomination": null}], "names": []}}, {"type": "StringLiteral", "value": "wallet is illegal"}], "names": []}}, {"type": "VariableDeclarationStatement", "variables": [{"type": "VariableDeclaration", "typeName": {"type": "UserDefinedTypeName", "namePath": "WalletInfo"}, "name": "walletInfo", "storageLocation": "storage"}], "initialValue": {"type": "IndexAccess", "base": {"type": "Identifier", "name": "walletTable"}, "index": {"type": "Identifier", "name": "_wallet"}}}, {"type": "IfStatement", "condition": {"type": "BinaryOperation", "operator": "<", "left": {"type": "MemberAccess", "expression": {"type": "Identifier", "name": "walletInfo"}, "memberName": "sequenceNum"}, "right": {"type": "Identifier", "name": "_sequenceNum"}}, "TrueBody": {"type": "Block", "statements": [{"type": "IfStatement", "condition": {"type": "BinaryOperation", "operator": "==", "left": {"type": "MemberAccess", "expression": {"type": "Identifier", "name": "walletInfo"}, "memberName": "sequenceNum"}, "right": {"type": "NumberLiteral", "number": "0", "subdenomination": null}}, "TrueBody": {"type": "ExpressionStatement", "expression": {"type": "BinaryOperation", "operator": "+=", "left": {"type": "Identifier", "name": "walletCount"}, "right": {"type": "NumberLiteral", "number": "1", "subdenomination": null}}}, "FalseBody": null}, {"type": "ExpressionStatement", "expression": {"type": "BinaryOperation", "operator": "=", "left": {"type": "MemberAccess", "expression": {"type": "Identifier", "name": "walletInfo"}, "memberName": "sequenceNum"}, "right": {"type": "Identifier", "name": "_sequenceNum"}}}, {"type": "ExpressionStatement", "expression": {"type": "BinaryOperation", "operator": "=", "left": {"type": "MemberAccess", "expression": {"type": "Identifier", "name": "walletInfo"}, "memberName": "isWhitelisted"}, "right": {"type": "Identifier", "name": "_isWhitelisted"}}}, {"type": "ExpressionStatement", "expression": {"type": "BinaryOperation", "operator": "=", "left": {"type": "MemberAccess", "expression": {"type": "Identifier", "name": "walletInfo"}, "memberName": "actionRole"}, "right": {"type": "Identifier", "name": "_actionRole"}}}, {"type": "ExpressionStatement", "expression": {"type": "BinaryOperation", "operator": "=", "left": {"type": "MemberAccess", "expression": {"type": "Identifier", "name": "walletInfo"}, "memberName": "buyLimit"}, "right": {"type": "Identifier", "name": "_buyLimit"}}}, {"type": "ExpressionStatement", "expression": {"type": "BinaryOperation", "operator": "=", "left": {"type": "MemberAccess", "expression": {"type": "Identifier", "name": "walletInfo"}, "memberName": "sellLimit"}, "right": {"type": "Identifier", "name": "_sellLimit"}}}, {"type": "ExpressionStatement", "expression": {"type": "BinaryOperation", "operator": "=", "left": {"type": "MemberAccess", "expression": {"type": "Identifier", "name": "walletInfo"}, "memberName": "tradeClass"}, "right": {"type": "Identifier", "name": "_tradeClass"}}}, {"type": "EmitStatement", "eventCall": {"type": "FunctionCall", "expression": {"type": "Identifier", "name": "WalletSaved"}, "arguments": [{"type": "Identifier", "name": "_wallet"}], "names": []}}]}, "FalseBody": {"type": "Block", "statements": [{"type": "EmitStatement", "eventCall": {"type": "FunctionCall", "expression": {"type": "Identifier", "name": "WalletNotSaved"}, "arguments": [{"type": "Identifier", "name": "_wallet"}], "names": []}}]}}]}, "visibility": "private", "modifiers": [], "isConstructor": false, "stateMutability": null}, {"type": "FunctionDefinition", "name": "_remove", "parameters": {"type": "ParameterList", "parameters": [{"type": "Parameter", "typeName": {"type": "ElementaryTypeName", "name": "address"}, "name": "_wallet", "storageLocation": null, "isStateVar": false, "isIndexed": false}]}, "returnParameters": [], "body": {"type": "Block", "statements": [{"type": "ExpressionStatement", "expression": {"type": "FunctionCall", "expression": {"type": "Identifier", "name": "require"}, "arguments": [{"type": "BinaryOperation", "operator": "!=", "left": {"type": "Identifier", "name": "_wallet"}, "right": {"type": "FunctionCall", "expression": {"type": "ElementaryTypeNameExpression", "typeName": {"type": "ElementaryTypeName", "name": "address"}}, "arguments": [{"type": "NumberLiteral", "number": "0", "subdenomination": null}], "names": []}}, {"type": "StringLiteral", "value": "wallet is illegal"}], "names": []}}, {"type": "VariableDeclarationStatement", "variables": [{"type": "VariableDeclaration", "typeName": {"type": "UserDefinedTypeName", "namePath": "WalletInfo"}, "name": "walletInfo", "storageLocation": "storage"}], "initialValue": {"type": "IndexAccess", "base": {"type": "Identifier", "name": "walletTable"}, "index": {"type": "Identifier", "name": "_wallet"}}}, {"type": "IfStatement", "condition": {"type": "BinaryOperation", "operator": ">", "left": {"type": "MemberAccess", "expression": {"type": "Identifier", "name": "walletInfo"}, "memberName": "sequenceNum"}, "right": {"type": "NumberLiteral", "number": "0", "subdenomination": null}}, "TrueBody": {"type": "Block", "statements": [{"type": "ExpressionStatement", "expression": {"type": "BinaryOperation", "operator": "-=", "left": {"type": "Identifier", "name": "walletCount"}, "right": {"type": "NumberLiteral", "number": "1", "subdenomination": null}}}, {"type": "ExpressionStatement", "expression": {"type": "UnaryOperation", "operator": "delete", "subExpression": {"type": "IndexAccess", "base": {"type": "Identifier", "name": "walletTable"}, "index": {"type": "Identifier", "name": "_wallet"}}, "isPrefix": true}}, {"type": "EmitStatement", "eventCall": {"type": "FunctionCall", "expression": {"type": "Identifier", "name": "WalletDeleted"}, "arguments": [{"type": "Identifier", "name": "_wallet"}], "names": []}}]}, "FalseBody": {"type": "Block", "statements": [{"type": "EmitStatement", "eventCall": {"type": "FunctionCall", "expression": {"type": "Identifier", "name": "WalletNotDeleted"}, "arguments": [{"type": "Identifier", "name": "_wallet"}], "names": []}}]}}]}, "visibility": "private", "modifiers": [], "isConstructor": false, "stateMutability": null}], "kind": "contract"}]}